lanscape/__init__.py
lanscape/__main__.py
lanscape/core/__init__.py
lanscape/core/app_scope.py
lanscape/core/decorators.py
lanscape/core/device_alive.py
lanscape/core/errors.py
lanscape/core/ip_parser.py
lanscape/core/logger.py
lanscape/core/mac_lookup.py
lanscape/core/net_tools.py
lanscape/core/port_manager.py
lanscape/core/runtime_args.py
lanscape/core/scan_config.py
lanscape/core/service_scan.py
lanscape/core/subnet_scan.py
lanscape/core/version_manager.py
lanscape/resources/mac_addresses/convert_csv.py
lanscape/resources/mac_addresses/mac_db.json
lanscape/resources/ports/convert_csv.py
lanscape/resources/ports/full.json
lanscape/resources/ports/large.json
lanscape/resources/ports/medium.json
lanscape/resources/ports/small.json
lanscape/resources/ports/test_port_list_scan.json
lanscape/resources/services/definitions.jsonc
lanscape/ui/__init__.py
lanscape/ui/app.py
lanscape/ui/main.py
lanscape/ui/shutdown_handler.py
lanscape/ui/blueprints/__init__.py
lanscape/ui/blueprints/api/__init__.py
lanscape/ui/blueprints/api/port.py
lanscape/ui/blueprints/api/scan.py
lanscape/ui/blueprints/api/tools.py
lanscape/ui/blueprints/web/__init__.py
lanscape/ui/blueprints/web/routes.py
lanscape/ui/static/lanscape.webmanifest
lanscape/ui/static/css/style.css
lanscape/ui/static/img/ico/android-chrome-192x192.png
lanscape/ui/static/img/ico/android-chrome-512x512.png
lanscape/ui/static/img/ico/apple-touch-icon.png
lanscape/ui/static/img/ico/favicon-16x16.png
lanscape/ui/static/img/ico/favicon-32x32.png
lanscape/ui/static/img/ico/favicon.ico
lanscape/ui/static/img/ico/site.webmanifest
lanscape/ui/static/js/core.js
lanscape/ui/static/js/layout-sizing.js
lanscape/ui/static/js/main.js
lanscape/ui/static/js/on-tab-close.js
lanscape/ui/static/js/quietReload.js
lanscape/ui/static/js/scan-config.js
lanscape/ui/static/js/shutdown-server.js
lanscape/ui/static/js/subnet-info.js
lanscape/ui/static/js/subnet-selector.js
lanscape/ui/templates/base.html
lanscape/ui/templates/error.html
lanscape-2.3.1.dist-info/licenses/LICENSE
lanscape-2.3.1.dist-info/METADATA
lanscape-2.3.1.dist-info/WHEEL
lanscape-2.3.1.dist-info/entry_points.txt
lanscape-2.3.1.dist-info/top_level.txt
lanscape-2.3.1.dist-info/RECORD
