Metadata-Version: 2.4
Name: lanscape
Version: 2.3.1
Summary: A python based local network scanner
Author-email: Michael Dennis <michael@dipduo.com>
License-Expression: MIT
Project-URL: Homepage, https://github.com/mdennis281/py-lanscape
Project-URL: Issues, https://github.com/mdennis281/py-lanscape/issues
Keywords: network,scanner,lan,local,python
Classifier: Programming Language :: Python :: 3
Classifier: Programming Language :: Python :: 3.10
Classifier: Programming Language :: Python :: 3.11
Classifier: Programming Language :: Python :: 3.12
Classifier: Programming Language :: Python :: 3.13
Classifier: Programming Language :: Python :: 3.14
Classifier: Operating System :: OS Independent
Requires-Python: >=3.10
License-File: LICENSE
Requires-Dist: Flask<5.0,>=3.0
Requires-Dist: psutil<7.0,>=6.0
Requires-Dist: requests<3.0,>=2.32
Requires-Dist: setuptools
Requires-Dist: scapy<3.0,>=2.3.2
Requires-Dist: tabulate==0.9.0
Requires-Dist: pydantic
Requires-Dist: icmplib
Requires-Dist: pwa-launcher>=1.1.0
Provides-Extra: dev
Requires-Dist: pytest>=8.0; extra == "dev"
Requires-Dist: pytest-cov>=5.0; extra == "dev"
Requires-Dist: pytest-xdist>=3.0; extra == "dev"
Requires-Dist: openai>=1.0.0; extra == "dev"
Requires-Dist: pylint>=3.0; extra == "dev"
Requires-Dist: autopep8>=2.0; extra == "dev"
Dynamic: license-file
